flyingtrain/__init__.py
flyingtrain-0.1.3.dist-info/LICENSE
flyingtrain-0.1.3.dist-info/METADATA
flyingtrain-0.1.3.dist-info/WHEEL
flyingtrain-0.1.3.dist-info/top_level.txt
flyingtrain-0.1.3.dist-info/RECORD
