Metadata-Version: 2.1
Name: flyingtrain
Version: 0.1.3
Summary: package for bonial challenge
Home-page: https://github.com/chuhsuanlee/flyingtrain
Author: Chu-Hsuan Lee
Author-email: joseph.chuhsuanlee@gmail.com
License: UNKNOWN
Platform: UNKNOWN
Classifier: Programming Language :: Python :: 2
Classifier: License :: OSI Approved :: MIT License
Classifier: Operating System :: OS Independent
Requires-Dist: ijson (==2.3)
